odoo/addons/repair_stock/README.rst
odoo/addons/repair_stock/__init__.py
odoo/addons/repair_stock/__manifest__.py
odoo/addons/repair_stock/i18n/it.po
odoo/addons/repair_stock/i18n/repair_stock.pot
odoo/addons/repair_stock/models/__init__.py
odoo/addons/repair_stock/models/repair.py
odoo/addons/repair_stock/models/stock_move.py
odoo/addons/repair_stock/models/stock_rule.py
odoo/addons/repair_stock/readme/CONTRIBUTORS.md
odoo/addons/repair_stock/readme/DESCRIPTION.md
odoo/addons/repair_stock/static/description/icon.png
odoo/addons/repair_stock/static/description/index.html
odoo/addons/repair_stock/tests/__init__.py
odoo/addons/repair_stock/tests/test_stock_repair_order.py
odoo/addons/repair_stock/views/repair_order_view.xml
odoo_addon_repair_stock-18.0.1.0.0.4.dist-info/METADATA
odoo_addon_repair_stock-18.0.1.0.0.4.dist-info/WHEEL
odoo_addon_repair_stock-18.0.1.0.0.4.dist-info/top_level.txt
odoo_addon_repair_stock-18.0.1.0.0.4.dist-info/RECORD
